RCA/Main/Full_Adder.v
module Full_adder(
    input A,
    input B,
    input Cin,
    output Sum,
    output Cout
);

assign Sum = A ^ B ^ Cin;
assign Cout = (A & B) | (A & Cin) | (B & Cin);

endmodule

FA/Main/Full_adder_tb.v
`timescale 1ns/1ps
module Full_Adder_tb;
reg  A;
reg B;
reg Cin;
wire Sum;
wire Cout;

Full_adder test(
    .A(A),
    .B(B),
    .Cin(Cin),
    .Sum(Sum),
    .Cout(Cout)
);

initial begin
    $dumpfile("Full_adder.vcd");
    $dumpvars(0, Full_Adder_tb);

    $monitor("Time=%0t | A=%b B=%b Cin=%b | Sum=%b Cout=%b",
    $time, A, B, Cin,Sum,Cout);

    A=0; B=0; Cin=0; #10
    A=0; B=0; Cin=1; #10
    A=0; B=1; Cin=0; #10
    A=0; B=1; Cin=1; #10
    A=1; B=0; Cin=0; #10
    A=1; B=0; Cin=1; #10
    A=1; B=1; Cin=0; #10
    A=1; B=1; Cin=1; #10

    $finish;

end
endmodule

FA/Main/Full_adder.vcd
$date
	Thu Aug 13 07:37:19 2026
$end
$version
	Icarus Verilog
$end
$timescale
	1ps
$end
$scope module Full_Adder_tb $end
$var wire 1 ! Sum $end
$var wire 1 " Cout $end
$var reg 1 # A $end
$var reg 1 $ B $end
$var reg 1 % Cin $end
$scope module test $end
$var wire 1 # A $end
$var wire 1 $ B $end
$var wire 1 % Cin $end
$var wire 1 " Cout $end
$var wire 1 ! Sum $end
$upscope $end
$upscope $end
$enddefinitions $end
$comment Show the parameter values. $end
$dumpall
$end
#0
$dumpvars
0%
0$
0#
0"
0!
$end
#10000
1!
1%
#20000
0%
1$
#30000
1"
0!
1%
#40000
0"
1!
0%
0$
1#
#50000
1"
0!
1%
#60000
0%
1$
#70000
1!
1%
