CodeConverter/Excess-3BCD/BCDtoExcess-3/Main/BCDtoExcess3.v
module BCDtoXS3(
    input A,B,C,D,
    output W, X, Y, Z
);

assign W = A | (B & C) | (B & D);
assign X = (~B & C) | (~B & D) | (B & ~C & ~D);
assign Y = (~C & ~D) | (C & D);
assign Z = ~D;

endmodule

CodeConverter/Excess-3BCD/BCDtoExcess-3/Main/BCDtoExcess-3_tb.v
`timescale 1ns/1ps
module BCDtoXS3_tb;
    reg A;
    reg B;
    reg C;
    reg D;
    wire W;
    wire X;
    wire Y;
    wire Z;

BCDtoXS3 UnitUnderTest(
    .A(A),
    .B(B),
    .C(C),
    .D(D),
    .W(W),
    .X(X),
    .Y(Y),
    .Z(Z)
);

initial begin
    $dumpfile("BCDtoXS3");
    $dumpvars(0, BCDtoXS3_tb);
    $monitor("time=%0t | A=%b B=%b C=%b D=%b | W=%b X=%b Y=%b Z=%b", $time, A,B,C,D,W,X,Y,Z);

    A = 0; B = 0; C = 0; D = 0; #10;
    A = 0; B = 0; C = 0; D = 1; #10;
    A = 0; B = 0; C = 1; D = 0; #10;
    A = 0; B = 0; C = 1; D = 1; #10;
    A = 0; B = 1; C = 0; D = 0; #10;
    A = 0; B = 1; C = 1; D = 0; #10;
    A = 0; B = 1; C = 1; D = 1; #10;
    A = 1; B = 0; C = 0; D = 0; #10;
    A = 1; B = 0; C = 0; D = 1; #10;
    

    $stop;
end
endmodule

CodeConverter/Excess-3BCD/BCDtoExcess-3/Main/BCDtoXS3.vcd
$date
	Sat Sep 12 08:27:04 2026
$end
$version
	Icarus Verilog
$end
$timescale
	1ps
$end
$scope module BCDtoXS3_tb $end
$var wire 1 ! Z $end
$var wire 1 " Y $end
$var wire 1 # X $end
$var wire 1 $ W $end
$var reg 1 % A $end
$var reg 1 & B $end
$var reg 1 ' C $end
$var reg 1 ( D $end
$scope module UnitUnderTest $end
$var wire 1 % A $end
$var wire 1 & B $end
$var wire 1 ' C $end
$var wire 1 ( D $end
$var wire 1 $ W $end
$var wire 1 # X $end
$var wire 1 " Y $end
$var wire 1 ! Z $end
$upscope $end
$upscope $end
$enddefinitions $end
$comment Show the parameter values. $end
$dumpall
$end
#0
$dumpvars
0(
0'
0&
0%
0$
0#
1"
1!
$end
#10000
1#
0"
0!
1(
#20000
1!
0(
1'
#30000
1"
0!
1(
#40000
1"
1!
0(
0'
1&
#50000
0#
1$
0"
1'
#60000
1"
0!
1(
#70000
1"
1!
0(
0'
0&
1%
#80000
1#
0"
0!
1(
