CodeConverter/Excess-3BCD/Excess-3toBCD/Main/XS3toBCD.v
module XS3toBCD(
 input [3:0] E,
 output [3:0] B
);

assign B[3] = (E[3] & E[2]) |
              (E[3] & E[1] & E[0]);
assign B[2] = (~E[2] & ~E[0]) |
              (~E[2] & ~E[1]) |
              (E[2] & E[1] & E[0]);
assign B[1] = (~E[1] & E[0]) |
              (E[1] & ~E[0]);
assign B[0] = ~E[0];

endmodule

CodeConverter/Excess-3BCD/Excess-3toBCD/Main/XS3toBCD_tb.v
module XS3toBCD_tb;
reg [3:0] E;
wire [3:0] B;

XS3toBCD uut(
    .E (E),
    .B (B)
);

initial begin
$dumpfile("XS3toBCD");
$dumpvars(0, XS3toBCD_tb);
$monitor("time=%0t | E=%b | B=%b",
$time, E, B);
E = 4'b0011; #10;
E = 4'b0100; #10;
E = 4'b0101; #10;
E = 4'b0110; #10;
E = 4'b0111; #10;
E = 4'b1000; #10;
E = 4'b1001; #10;
E = 4'b1010; #10;
E = 4'b1011; #10;
E = 4'b1100; #10;
$stop;
end
endmodule

CodeConverter/Excess-3BCD/Excess-3toBCD/Main/XS3toBCD.vcd
$date
	Sun Sep 13 13:46:36 2026
$end
$version
	Icarus Verilog
$end
$timescale
	1s
$end
$scope module XS3toBCD_tb $end
$var wire 4 ! B [3:0] $end
$var reg 4 " E [3:0] $end
$scope module uut $end
$var wire 4 # E [3:0] $end
$var wire 4 $ B [3:0] $end
$upscope $end
$upscope $end
$enddefinitions $end
$comment Show the parameter values. $end
$dumpall
$end
#0
$dumpvars
b0 $
b11 #
b11 "
b0 !
$end
#10
b1 !
b1 $
b100 "
b100 #
#20
b10 !
b10 $
b101 "
b101 #
#30
b11 !
b11 $
b110 "
b110 #
#40
b100 !
b100 $
b111 "
b111 #
#50
b101 !
b101 $
b1000 "
b1000 #
#60
b110 !
b110 $
b1001 "
b1001 #
#70
b111 !
b111 $
b1010 "
b1010 #
#80
b1000 !
b1000 $
b1011 "
b1011 #
#90
b1001 !
b1001 $
b1100 "
b1100 #
