CodeConverter/BinaryGray/BinarytoGray/Main/BG.v
module BinarytoGray(
    input [3:0] B,
    output [3:0] G
);

assign G[3] = B[3];
assign G[2] = B[3] ^ B[2];
assign G[1] = B[2] ^ B[1];
assign G[0] = B[1] ^ B[0];

endmodule

CodeConverter/BinaryGray/BinarytoGray/Main/BG_tb.v
`timescale 1ns/1ps
module BinarytoGray_tb;
    reg [3:0] B;
    wire [3:0] G;

    BinarytoGray uut(
        .B(B),
        .G(G)
    );

initial begin
    $dumpfile("BG.vcd");
    $dumpvars(0, BinarytoGray_tb);
    
    $monitor("time=%0t | B=%b | G=%b ",$time, B, G);
    B=4'b0000; #10;
    B=4'b0001; #10;
    B=4'b0010; #10;
    B=4'b0011; #10;
    B=4'b0100; #10;
    B=4'b0101; #10;
    B=4'b0110; #10;
    B=4'b0111; #10;
    B=4'b1000; #10;
    B=4'b1001; #10;
    B=4'b1010; #10;
    B=4'b1011; #10;
    B=4'b1100; #10;
    B=4'b1101; #10;
    B=4'b1110; #10;
    B=4'b1111; #10;

    $finish;
end

endmodule

//Verification successed

CodeConverter/BinaryGray/BinarytoGray/Main/BG.vcd
$date
	Sun Sep  6 14:07:41 2026
$end
$version
	Icarus Verilog
$end
$timescale
	1ps
$end
$scope module BinarytoGray_tb $end
$var wire 4 ! G [3:0] $end
$var reg 4 " B [3:0] $end
$scope module uut $end
$var wire 4 # B [3:0] $end
$var wire 4 $ G [3:0] $end
$upscope $end
$upscope $end
$enddefinitions $end
$comment Show the parameter values. $end
$dumpall
$end
#0
$dumpvars
b0 $
b0 #
b0 "
b0 !
$end
#10000
b1 !
b1 $
b1 "
b1 #
#20000
b11 !
b11 $
b10 "
b10 #
#30000
b10 !
b10 $
b11 "
b11 #
#40000
b110 !
b110 $
b100 "
b100 #
#50000
b111 !
b111 $
b101 "
b101 #
#60000
b101 !
b101 $
b110 "
b110 #
#70000
b100 !
b100 $
b111 "
b111 #
#80000
b1100 !
b1100 $
b1000 "
b1000 #
#90000
b1101 !
b1101 $
b1001 "
b1001 #
#100000
b1111 !
b1111 $
b1010 "
b1010 #
#110000
b1110 !
b1110 $
b1011 "
b1011 #
#120000
b1010 !
b1010 $
b1100 "
b1100 #
#130000
b1011 !
b1011 $
b1101 "
b1101 #
#140000
b1001 !
b1001 $
b1110 "
b1110 #
#150000
b1000 !
b1000 $
b1111 "
b1111 #
