Subtractors/fullSub/Main/hs.v
module hs_sub(
    input A,
    input B,
    output D,
    output Borrow
);
assign D = A ^ B;
assign Borrow = ~A & B;

endmodule

Subtractors/fullSub/Main/fs.v
module fs(
    input A,
    input B,
    input Bin,
    output D,
    output Bout
);
wire D1;
wire Borrow1;
wire Borrow2;

hs_sub HS1(
    .A (A),
    .B (B),
    .D (D1),
    .Borrow (Borrow1)
);
hs_sub HS2(
    .A (D1),
    .B (Bin),
    .D (D),
    .Borrow (Borrow2)
);

assign Bout = Borrow1 | Borrow2;

endmodule

Subtractors/fullSub/Main/fs_tb.v
`timescale 1ns/1ps
module FS_tb;
reg A;
reg B;
reg Bin;

wire D;
wire Bout;

fs uut(
    .A (A),
    .B (B),
    .Bin (Bin),
    .D (D),
    .Bout (Bout)
);

initial begin
    $dumpfile("FS.vcd");
    $dumpvars(0, FS_tb);
    $display("A B Bin | D Bout");
    $display("----------------");

A=0;B=0;Bin=0; #10;
$display("%b %b %b | %b %b", A, B, Bin, D, Bout);
A=0;B=0;Bin=1; #10;
$display("%b %b %b | %b %b", A, B, Bin, D, Bout);
A=0;B=1;Bin=0; #10;
$display("%b %b %b | %b %b", A, B, Bin, D, Bout);
A=0;B=1;Bin=1; #10;
$display("%b %b %b | %b %b", A, B, Bin, D, Bout);
A=1;B=0;Bin=0; #10;
$display("%b %b %b | %b %b", A, B, Bin, D, Bout);
A=1;B=0;Bin=1; #10;
$display("%b %b %b | %b %b", A, B, Bin, D, Bout);
A=1;B=1;Bin=0; #10;
$display("%b %b %b | %b %b", A, B, Bin, D, Bout);
A=1;B=1;Bin=1; #10;
$display("%b %b %b | %b %b", A, B, Bin, D, Bout);
$finish;
end

endmodule

Subtractors/fullSub/Main/FS.vcd
$date
	Fri Aug 28 13:48:52 2026
$end
$version
	Icarus Verilog
$end
$timescale
	1ps
$end
$scope module FS_tb $end
$var wire 1 ! D $end
$var wire 1 " Bout $end
$var reg 1 # A $end
$var reg 1 $ B $end
$var reg 1 % Bin $end
$scope module uut $end
$var wire 1 # A $end
$var wire 1 $ B $end
$var wire 1 % Bin $end
$var wire 1 " Bout $end
$var wire 1 & D1 $end
$var wire 1 ! D $end
$var wire 1 ' Borrow2 $end
$var wire 1 ( Borrow1 $end
$scope module HS1 $end
$var wire 1 # A $end
$var wire 1 $ B $end
$var wire 1 ( Borrow $end
$var wire 1 & D $end
$upscope $end
$scope module HS2 $end
$var wire 1 & A $end
$var wire 1 % B $end
$var wire 1 ' Borrow $end
$var wire 1 ! D $end
$upscope $end
$upscope $end
$upscope $end
$enddefinitions $end
$comment Show the parameter values. $end
$dumpall
$end
#0
$dumpvars
0(
0'
0&
0%
0$
0#
0"
0!
$end
#10000
1"
1!
1'
1%
#20000
0'
1&
1(
0%
1$
#30000
0!
1%
#40000
0"
1!
0(
0%
0$
1#
#50000
0!
1%
#60000
0&
0%
1$
#70000
1"
1!
1'
1%
