Decoder/4to16Decoder/Main/decoder.v
module decoderFS(
    input A,
    input B,
    input C,
    input D,
    output D0,
    output D1,
    output D2,
    output D3,
    output D4,
    output D5,
    output D6,
    output D7,
    output D8,
    output D9,
    output D10,
    output D11,
    output D12,
    output D13,
    output D14,
    output D15
);

assign D0 = ~A & ~B & ~C & ~D;
assign D1 = ~A & ~B & ~C & D;
assign D2 = ~A & ~B & C & ~D;
assign D3 = ~A & ~B & C & D;
assign D4 = ~A & B & ~C & ~D;
assign D5 = ~A & B & ~C & D;
assign D6 = ~A & B & C & ~D;
assign D7 = ~A & A & C & D;
assign D8 = A & ~B & ~C & ~D;
assign D9 = A & ~B & ~C & D;
assign D10 = A & ~B & C & ~D;
assign D11 = A & ~B & C & D;
assign D12 = A & B & ~C & ~D;
assign D13 = A & B & ~C & D;
assign D14 = A & B & C & ~D;
assign D15 = A & B & C & D;

endmodule

Decoder/4to16Decoder/Main/decoder_tb.v
module decoderFS_tb;
reg A;
reg B;
reg C; 
reg D;
wire D0;
wire D1;
wire D2;
wire D3;
wire D4;
wire D5;
wire D6;
wire D7;
wire D8;
wire D9;
wire D10;
wire D11;
wire D12;
wire D13;
wire D14;
wire D15;

decoderFS uut(
    .A(A),
    .B(B),
    .C(C),
    .D(D),
    .D0(D0),
    .D1(D1),
    .D2(D2),
    .D3(D3),
    .D4(D4),
    .D5(D5),
    .D6(D6),
    .D7(D7),
    .D8(D8),
    .D9(D9),
    .D10(D10),
    .D11(D11),
    .D12(D12),
    .D13(D13),
    .D14(D14),
    .D15(D15)
);

initial begin
    $dumpfile("decoder.vcd");
    $dumpvars(0, decoderFS_tb);

    A = 0; B = 0; C = 0; D = 0; #10;
    A = 0; B = 0; C = 0; D = 1; #10;
    A = 0; B = 0; C = 1; D = 0; #10;
    A = 0; B = 0; C = 1; D = 1; #10;
    A = 0; B = 1; C = 0; D = 0; #10;
    A = 0; B = 1; C = 0; D = 1; #10;
    A = 0; B = 1; C = 1; D = 0; #10;
    A = 0; B = 1; C = 1; D = 1; #10;
    A = 1; B = 0; C = 0; D = 0; #10;
    A = 1; B = 0; C = 0; D = 1; #10;
    A = 1; B = 0; C = 1; D = 0; #10;
    A = 1; B = 0; C = 1; D = 1; #10;
    A = 1; B = 1; C = 0; D = 0; #10;
    A = 1; B = 1; C = 0; D = 1; #10;
    A = 1; B = 1; C = 1; D = 0; #10;
    A = 1; B = 1; C = 1; D = 1; #10;

    $finish;
end

endmodule

Decoder/4to16Decoder/Main/decoder.vcd
$date
	Fri Aug 14 17:50:19 2026
$end
$version
	Icarus Verilog
$end
$timescale
	1s
$end
$scope module decoderFS_tb $end
$var wire 1 ! D9 $end
$var wire 1 " D8 $end
$var wire 1 # D7 $end
$var wire 1 $ D6 $end
$var wire 1 % D5 $end
$var wire 1 & D4 $end
$var wire 1 ' D3 $end
$var wire 1 ( D2 $end
$var wire 1 ) D15 $end
$var wire 1 * D14 $end
$var wire 1 + D13 $end
$var wire 1 , D12 $end
$var wire 1 - D11 $end
$var wire 1 . D10 $end
$var wire 1 / D1 $end
$var wire 1 0 D0 $end
$var reg 1 1 A $end
$var reg 1 2 B $end
$var reg 1 3 C $end
$var reg 1 4 D $end
$scope module uut $end
$var wire 1 1 A $end
$var wire 1 2 B $end
$var wire 1 3 C $end
$var wire 1 4 D $end
$var wire 1 0 D0 $end
$var wire 1 / D1 $end
$var wire 1 . D10 $end
$var wire 1 - D11 $end
$var wire 1 , D12 $end
$var wire 1 + D13 $end
$var wire 1 * D14 $end
$var wire 1 ) D15 $end
$var wire 1 ( D2 $end
$var wire 1 ' D3 $end
$var wire 1 & D4 $end
$var wire 1 % D5 $end
$var wire 1 $ D6 $end
$var wire 1 # D7 $end
$var wire 1 " D8 $end
$var wire 1 ! D9 $end
$upscope $end
$upscope $end
$enddefinitions $end
$comment Show the parameter values. $end
$dumpall
$end
#0
$dumpvars
04
03
02
01
10
0/
0.
0-
0,
0+
0*
0)
0(
0'
0&
0%
0$
0#
0"
0!
$end
#10
00
1/
14
#20
1(
0/
04
13
#30
0(
1'
14
#40
1&
0'
04
03
12
#50
0&
1%
14
#60
1$
0%
04
13
#70
0$
14
#80
1"
04
03
02
11
#90
0"
1!
14
#100
1.
0!
04
13
#110
0.
1-
14
#120
1,
0-
04
03
12
#130
0,
1+
14
#140
1*
0+
04
13
#150
0*
1)
14
