Comparator/2bit/Main/comp.v
module twoBC(
    input [1:0] A,
    input [1:0] B,
    output G,
    output E,
    output L
);

assign G = A[1] & ~B[1] | (A[1] ~^ B[1]) & (A[0] & ~B[0]);
assign E = (A[1] ~^ B[1]) & (A[0] ~^ B[0]);
assign L = ~A[1] & B[1] | (A[1] ~^ B[1]) & (~A[0] & B[0]);

endmodule

Comparator/2bit/Main/comp_tb.v
`timescale 1ns/1ps
module twoBC_tb;
reg [1:0] A;
reg [1:0] B;
wire G;
wire E;
wire L;

twoBC uut(
    .A(A),
    .B(B),
    .G(G),
    .E(E),
    .L(L)
);

initial begin
    $dumpfile("Comp.vcd");
    $dumpvars(0, twoBC_tb);
    $monitor("Time=%0t | A=%b B=%b | G=%b E=%b L=%b",
    $time, A, B, G,E,L);

    A=2'b00; B=2'b00;#10;
    A=2'b00; B=2'b01;#10;
    A=2'b00; B=2'b10;#10;
    A=2'b00; B=2'b11;#10;
    A=2'b01; B=2'b00;#10;
    A=2'b01; B=2'b01;#10;
    A=2'b01; B=2'b10;#10;
    A=2'b01; B=2'b11;#10;
    A=2'b10; B=2'b10;#10;
    A=2'b10; B=2'b01;#10;
    A=2'b10; B=2'b10;#10;
    A=2'b10; B=2'b11;#10;
    A=2'b11; B=2'b00;#10;
    A=2'b11; B=2'b01;#10;
    A=2'b11; B=2'b10;#10;
    A=2'b11; B=2'b11;#10;

 

    $finish;
    
   
    


end
endmodule

Comparator/2bit/Main/Comp.vcd
$date
	Fri Aug 21 06:48:37 2026
$end
$version
	Icarus Verilog
$end
$timescale
	1ps
$end
$scope module twoBC_tb $end
$var wire 1 ! L $end
$var wire 1 " G $end
$var wire 1 # E $end
$var reg 2 $ A [1:0] $end
$var reg 2 % B [1:0] $end
$scope module uut $end
$var wire 2 & A [1:0] $end
$var wire 2 ' B [1:0] $end
$var wire 1 # E $end
$var wire 1 " G $end
$var wire 1 ! L $end
$upscope $end
$upscope $end
$enddefinitions $end
$comment Show the parameter values. $end
$dumpall
$end
#0
$dumpvars
b0 '
b0 &
b0 %
b0 $
1#
0"
0!
$end
#10000
1!
0#
b1 %
b1 '
#20000
b10 %
b10 '
#30000
b11 %
b11 '
#40000
1"
0!
b0 %
b0 '
b1 $
b1 &
#50000
0"
1#
b1 %
b1 '
#60000
0#
1!
b10 %
b10 '
#70000
b11 %
b11 '
#80000
0!
1#
b10 %
b10 '
b10 $
b10 &
#90000
1"
0#
b1 %
b1 '
#100000
0"
1#
b10 %
b10 '
#110000
1!
0#
b11 %
b11 '
#120000
1"
0!
b0 %
b0 '
b11 $
b11 &
#130000
b1 %
b1 '
#140000
b10 %
b10 '
#150000
0"
1#
b11 %
b11 '
