CodeConverter/BinaryGray/GraytoBinary/Main/GB.v
module GraytoBinary(
    input wire [3:0] G,
    output wire [3:0] B
);
assign B[3] = G[3];
assign B[2] = B[3] ^ G[2];
assign B[1] = B[2] ^ G[1];
assign B[0] = B[1] ^ G[0];

endmodule

CodeConverter/BinaryGray/GraytoBinary/Main/GB_tb.v
`timescale 1ns/1ps
module GraytoBinary_tb;
    reg [3:0] G;
    wire [3:0] B;

GraytoBinary uut(
    .G (G),
    .B (B)
);

initial begin
    $dumpfile("GB.vcd");
    $dumpvars(0, GraytoBinary_tb);
    
    $monitor("time=%0t | G=%b | B=%b",
     $time, G, B);

    G=4'b0000; #10;
    G=4'b0001; #10;
    G=4'b0011; #10;
    G=4'b0010; #10;
    G=4'b0110; #10;
    G=4'b0111; #10;
    G=4'b0101; #10;
    G=4'b0100; #10;

    $finish;

end

endmodule

CodeConverter/BinaryGray/GraytoBinary/Main/GB.vcd
$date
	Sun Sep  6 16:30:16 2026
$end
$version
	Icarus Verilog
$end
$timescale
	1ps
$end
$scope module GraytoBinary_tb $end
$var wire 4 ! B [3:0] $end
$var reg 4 " G [3:0] $end
$scope module uut $end
$var wire 4 # G [3:0] $end
$var wire 4 $ B [3:0] $end
$upscope $end
$upscope $end
$enddefinitions $end
$comment Show the parameter values. $end
$dumpall
$end
#0
$dumpvars
b0 $
b0 #
b0 "
b0 !
$end
#10000
b1 !
b1 $
b1 "
b1 #
#20000
b10 !
b10 $
b11 "
b11 #
#30000
b11 !
b11 $
b10 "
b10 #
#40000
b100 !
b100 $
b110 "
b110 #
#50000
b101 !
b101 $
b111 "
b111 #
#60000
b110 !
b110 $
b101 "
b101 #
#70000
b111 !
b111 $
b100 "
b100 #
