Encoder/PriorityEncoder/Main/PEncoder.v
module PEncode(
    input D3,
    input D2,
    input D1,
    input D0,
    output reg Y1,
    output reg Y0,
    output reg V
);
always @(*) begin
    
//default values
Y1 = 0;
Y0 = 0;
V = 0;

if(D3)begin
Y1 = 1;
Y0 = 1;
V = 1;
end

else if(D2)begin
Y1 = 1;
Y0 = 0;
V = 1;
end

else if(D1)begin
Y1 = 0;
Y0 = 1;
V = 1;
end

else if(D0)begin
Y1 = 0;
Y0 = 0;
V = 1;
end

end

endmodule

Encoder/PriorityEncoder/Main/PEncoder_tb.v
`timescale 1ns/1ps
module Pencoder_tb;
reg D3, D2, D1, D0;
wire Y1, Y0, V;

PEncode uut(
    .D3(D3),
    .D2(D2),
    .D1(D1),
    .D0(D0),
    .Y1(Y1),
    .Y0(Y0),
    .V(V)
);

initial begin

$dumpfile("PEncoder.vcd");
$dumpvars(0, Pencoder_tb);

    D3 = 0; D2 = 0; D1 = 0; D0 = 0;
    #10;
    D3 = 0; D2 = 0; D1 = 0; D0 = 1;
    #10;
    D3 = 0; D2 = 0; D1 = 1; D0 = 0;
    #10;
    D3 = 0; D2 = 0; D1 = 1; D0 = 1;
    #10;
    D3 = 0; D2 = 1; D1 = 0; D0 = 0;
    #10;
    D3 = 0; D2 = 1; D1 = 1; D0 = 0;
    #10;
    D3 = 0; D2 = 1; D1 = 1; D0 = 1;
    #10;
    D3 = 1; D2 = 0; D1 = 0; D0 = 0;
    #10;
    D3 = 1; D2 = 1; D1 = 1; D0 = 1;
    #10;

    $finish;
end
endmodule

Encoder/PriorityEncoder/Main/PEncoder.vcd
$date
	Mon Aug 17 14:53:23 2026
$end
$version
	Icarus Verilog
$end
$timescale
	1ps
$end
$scope module Pencoder_tb $end
$var wire 1 ! Y1 $end
$var wire 1 " Y0 $end
$var wire 1 # V $end
$var reg 1 $ D0 $end
$var reg 1 % D1 $end
$var reg 1 & D2 $end
$var reg 1 ' D3 $end
$scope module uut $end
$var wire 1 $ D0 $end
$var wire 1 % D1 $end
$var wire 1 & D2 $end
$var wire 1 ' D3 $end
$var reg 1 # V $end
$var reg 1 " Y0 $end
$var reg 1 ! Y1 $end
$upscope $end
$upscope $end
$enddefinitions $end
$comment Show the parameter values. $end
$dumpall
$end
#0
$dumpvars
0'
0&
0%
0$
0#
0"
0!
$end
#10000
1#
1$
#20000
1"
1#
0$
1%
#30000
1#
1"
1$
#40000
1!
1#
0"
0$
0%
1&
#50000
1#
1!
1%
#60000
1#
1!
1$
#70000
1"
1#
1!
0$
0%
0&
1'
#80000
1#
1"
1!
1$
1%
1&
