Decoder/3toDecoder/Main/decoder.v
module DecoderTE(
    input A,
    input B,
    input C,
    output D0,
    output D1,
    output D2,
    output D3,
    output D4,
    output D5,
    output D6,
    output D7
);

assign D0 = ~A & ~B & ~C;
assign D1 = ~A & ~B & C;
assign D2 = ~A & B & ~C;
assign D3 = ~A & B & C;
assign D4 = A & ~B & ~C;
assign D5 = A & ~B & C;
assign D6 = A & B & ~C;
assign D7 = A & B & C;

endmodule

Decoder/3toDecoder/Main/decoder_tb.v
module Decoder_tb;
reg A;
reg B;
reg C;

wire D0;
wire D1;
wire D2;
wire D3;
wire D4;
wire D5;
wire D6;
wire D7;

DecoderTE uut(
    .A(A),
    .B(B),
    .C(C),
    .D0(D0),
    .D1(D1),
    .D2(D2),
    .D3(D3),
    .D4(D4),
    .D5(D5),
    .D6(D6),
    .D7(D7)
);

initial begin
    $dumpfile("Decoder.vcd");
    $dumpvars(0, Decoder_tb);

    A = 0; B = 0; C = 0; #10;
    A = 0; B = 0; C = 1; #10;
    A = 0; B = 1; C = 0; #10;
    A = 0; B = 1; C = 1; #10;
    A = 1; B = 0; C = 0; #10;
    A = 1; B = 0; C = 1; #10;
    A = 1; B = 1; C = 0; #10;
    A = 1; B = 1; C = 1; #10;

    $finish;
end

endmodule

Decoder/3toDecoder/Main/Decoder.vcd
$date
	Fri Aug 14 16:56:27 2026
$end
$version
	Icarus Verilog
$end
$timescale
	1s
$end
$scope module Decoder_tb $end
$var wire 1 ! D7 $end
$var wire 1 " D6 $end
$var wire 1 # D5 $end
$var wire 1 $ D4 $end
$var wire 1 % D3 $end
$var wire 1 & D2 $end
$var wire 1 ' D1 $end
$var wire 1 ( D0 $end
$var reg 1 ) A $end
$var reg 1 * B $end
$var reg 1 + C $end
$scope module uut $end
$var wire 1 ) A $end
$var wire 1 * B $end
$var wire 1 + C $end
$var wire 1 ( D0 $end
$var wire 1 ' D1 $end
$var wire 1 & D2 $end
$var wire 1 % D3 $end
$var wire 1 $ D4 $end
$var wire 1 # D5 $end
$var wire 1 " D6 $end
$var wire 1 ! D7 $end
$upscope $end
$upscope $end
$enddefinitions $end
$comment Show the parameter values. $end
$dumpall
$end
#0
$dumpvars
0+
0*
0)
1(
0'
0&
0%
0$
0#
0"
0!
$end
#10
0(
1'
1+
#20
1&
0'
0+
1*
#30
0&
1%
1+
#40
1$
0%
0+
0*
1)
#50
0$
1#
1+
#60
1"
0#
0+
1*
#70
0"
1!
1+
